[
  {
    "number": 0,
    "value": 0.17972893241143276,
    "params": {
      "max_depth": 5,
      "learning_rate": 0.24517932047070642,
      "min_child_weight": 75,
      "gamma": 0.5986584841970366,
      "subsample": 0.5780093202212182,
      "colsample_bytree": 0.40919616423534183,
      "reg_alpha": 3.3323645788192616e-08,
      "reg_lambda": 0.6245760287469893,
      "scale_pos_weight": 37.27940375042845
    },
    "user_attrs": {
      "device": "cuda",
      "n_estimators_used": 59,
      "val_auroc": 0.8874556507419534
    }
  },
  {
    "number": 1,
    "value": 0.14763789120133824,
    "params": {
      "max_depth": 7,
      "learning_rate": 0.005439667429522981,
      "min_child_weight": 98,
      "gamma": 0.8324426408004217,
      "subsample": 0.6061695553391381,
      "colsample_bytree": 0.42727747704497043,
      "reg_alpha": 4.4734294104626844e-07,
      "reg_lambda": 5.472429642032198e-06,
      "scale_pos_weight": 32.670895056523506
    },
    "user_attrs": {
      "device": "cuda",
      "n_estimators_used": 15,
      "val_auroc": 0.8701016350134254
    }
  },
  {
    "number": 2,
    "value": 0.15442748928279632,
    "params": {
      "max_depth": 5,
      "learning_rate": 0.01647477394109053,
      "min_child_weight": 63,
      "gamma": 0.13949386065204183,
      "subsample": 0.6460723242676091,
      "colsample_bytree": 0.5564532903055841,
      "reg_alpha": 0.00012724181576752517,
      "reg_lambda": 0.1165691561324743,
      "scale_pos_weight": 13.051014564235878
    },
    "user_attrs": {
      "device": "cuda",
      "n_estimators_used": 10,
      "val_auroc": 0.867697448781535
    }
  },
  {
    "number": 3,
    "value": 0.20728739430196888,
    "params": {
      "max_depth": 6,
      "learning_rate": 0.056542201075504325,
      "min_child_weight": 9,
      "gamma": 0.6075448519014384,
      "subsample": 0.5852620618436457,
      "colsample_bytree": 0.3455361150896956,
      "reg_alpha": 3.4671276804481113,
      "reg_lambda": 4.905556676028774,
      "scale_pos_weight": 49.789621303986834
    },
    "user_attrs": {
      "device": "cuda",
      "n_estimators_used": 242,
      "val_auroc": 0.8963273108109184
    }
  },
  {
    "number": 4,
    "value": 0.1482723372911287,
    "params": {
      "max_depth": 4,
      "learning_rate": 0.007458402142772737,
      "min_child_weight": 70,
      "gamma": 0.4401524937396013,
      "subsample": 0.5610191174223894,
      "colsample_bytree": 0.6466238370778892,
      "reg_alpha": 2.039373116525212e-08,
      "reg_lambda": 1.527156759251193,
      "scale_pos_weight": 16.618281446290176
    },
    "user_attrs": {
      "device": "cuda",
      "n_estimators_used": 4,
      "val_auroc": 0.8556443002674253
    }
  },
  {
    "number": 5,
    "value": 0.1624690008594823,
    "params": {
      "max_depth": 6,
      "learning_rate": 0.017915933593754683,
      "min_child_weight": 54,
      "gamma": 0.5467102793432796,
      "subsample": 0.5924272277627636,
      "colsample_bytree": 0.9787092394351908,
      "reg_alpha": 0.09466630153726856,
      "reg_lambda": 2.854239907497756,
      "scale_pos_weight": 55.005975726587
    },
    "user_attrs": {
      "device": "cuda",
      "n_estimators_used": 29,
      "val_auroc": 0.8739645179898009
    }
  },
  {
    "number": 6,
    "value": 0.189526090555712,
    "params": {
      "max_depth": 6,
      "learning_rate": 0.21787220464104293,
      "min_child_weight": 13,
      "gamma": 0.1959828624191452,
      "subsample": 0.522613644455269,
      "colsample_bytree": 0.527731231534285,
      "reg_alpha": 3.148441347423712e-05,
      "reg_lambda": 2.7678419414850017e-06,
      "scale_pos_weight": 51.01722151382774
    },
    "user_attrs": {
      "device": "cuda",
      "n_estimators_used": 219,
      "val_auroc": 0.8823295972708878
    }
  },
  {
    "number": 7,
    "value": 0.19656295489553022,
    "params": {
      "max_depth": 5,
      "learning_rate": 0.015794797197594638,
      "min_child_weight": 57,
      "gamma": 0.14092422497476265,
      "subsample": 0.9010984903770198,
      "colsample_bytree": 0.35218545057583955,
      "reg_alpha": 7.620481786158549,
      "reg_lambda": 0.08916674715636537,
      "scale_pos_weight": 12.993189824045762
    },
    "user_attrs": {
      "device": "cuda",
      "n_estimators_used": 1084,
      "val_auroc": 0.8929636388211752
    }
  },
  {
    "number": 8,
    "value": 0.17842402694069093,
    "params": {
      "max_depth": 3,
      "learning_rate": 0.1409236110165583,
      "min_child_weight": 72,
      "gamma": 0.7290071680409873,
      "subsample": 0.8856351733429728,
      "colsample_bytree": 0.35183125621386324,
      "reg_alpha": 1.683416412018213e-05,
      "reg_lambda": 1.1036250149900698e-07,
      "scale_pos_weight": 53.09132537700663
    },
    "user_attrs": {
      "device": "cuda",
      "n_estimators_used": 170,
      "val_auroc": 0.885959941731167
    }
  },
  {
    "number": 9,
    "value": 0.15716374010913325,
    "params": {
      "max_depth": 6,
      "learning_rate": 0.0193801324564921,
      "min_child_weight": 11,
      "gamma": 0.3109823217156622,
      "subsample": 0.6625916610133735,
      "colsample_bytree": 0.8107243248366449,
      "reg_alpha": 0.005470376807480391,
      "reg_lambda": 0.9658611176861268,
      "scale_pos_weight": 29.499830468794247
    },
    "user_attrs": {
      "device": "cuda",
      "n_estimators_used": 15,
      "val_auroc": 0.8715047907855216
    }
  },
  {
    "number": 10,
    "value": 0.19939701089609005,
    "params": {
      "max_depth": 8,
      "learning_rate": 0.07156112147849181,
      "min_child_weight": 29,
      "gamma": 0.9322903419117872,
      "subsample": 0.7595720016297407,
      "colsample_bytree": 0.7831729514984016,
      "reg_alpha": 5.724692232873258,
      "reg_lambda": 0.0025074987853267337,
      "scale_pos_weight": 40.71033046048031
    },
    "user_attrs": {
      "device": "cuda",
      "n_estimators_used": 169,
      "val_auroc": 0.8896843964377932
    }
  },
  {
    "number": 11,
    "value": 0.2261478054499938,
    "params": {
      "max_depth": 8,
      "learning_rate": 0.07048691928749572,
      "min_child_weight": 28,
      "gamma": 0.9621618041817265,
      "subsample": 0.7795107662780011,
      "colsample_bytree": 0.791889462930599,
      "reg_alpha": 5.166521327103313,
      "reg_lambda": 0.0014737528144782958,
      "scale_pos_weight": 42.86136720717742
    },
    "user_attrs": {
      "device": "cuda",
      "n_estimators_used": 593,
      "val_auroc": 0.8946532225827383
    }
  },
  {
    "number": 12,
    "value": 0.2370380929302467,
    "params": {
      "max_depth": 8,
      "learning_rate": 0.06776858343728658,
      "min_child_weight": 33,
      "gamma": 0.9972257164264666,
      "subsample": 0.7506588367811431,
      "colsample_bytree": 0.8024221872389928,
      "reg_alpha": 0.0885760096502798,
      "reg_lambda": 0.0011609250063879415,
      "scale_pos_weight": 60.83412339145292
    },
    "user_attrs": {
      "device": "cuda",
      "n_estimators_used": 483,
      "val_auroc": 0.8933130809998219
    }
  },
  {
    "number": 13,
    "value": 0.197876947045236,
    "params": {
      "max_depth": 8,
      "learning_rate": 0.0718744556892977,
      "min_child_weight": 34,
      "gamma": 0.9993624386415512,
      "subsample": 0.783956968399597,
      "colsample_bytree": 0.838568165647844,
      "reg_alpha": 0.1191260603733718,
      "reg_lambda": 0.0006178317394192874,
      "scale_pos_weight": 61.277431826552856
    },
    "user_attrs": {
      "device": "cuda",
      "n_estimators_used": 160,
      "val_auroc": 0.891090719770308
    }
  },
  {
    "number": 14,
    "value": 0.15812341297888244,
    "params": {
      "max_depth": 8,
      "learning_rate": 0.037057866950902504,
      "min_child_weight": 35,
      "gamma": 0.7845942007687469,
      "subsample": 0.9964863743704975,
      "colsample_bytree": 0.9302723308626759,
      "reg_alpha": 0.11925517503176895,
      "reg_lambda": 0.004633011838829117,
      "scale_pos_weight": 24.65959698360226
    },
    "user_attrs": {
      "device": "cuda",
      "n_estimators_used": 6,
      "val_auroc": 0.8603967642924117
    }
  },
  {
    "number": 15,
    "value": 0.21023795589829547,
    "params": {
      "max_depth": 7,
      "learning_rate": 0.1252314295251389,
      "min_child_weight": 43,
      "gamma": 0.8957113115891051,
      "subsample": 0.8202139292383122,
      "colsample_bytree": 0.7222565168309547,
      "reg_alpha": 0.00544460501961048,
      "reg_lambda": 1.8403817592501964e-05,
      "scale_pos_weight": 43.30845667089168
    },
    "user_attrs": {
      "device": "cuda",
      "n_estimators_used": 166,
      "val_auroc": 0.8940833625049165
    }
  },
  {
    "number": 16,
    "value": 0.23401615335884413,
    "params": {
      "max_depth": 7,
      "learning_rate": 0.036224089863577336,
      "min_child_weight": 26,
      "gamma": 0.707616070841413,
      "subsample": 0.7069358360469239,
      "colsample_bytree": 0.8841716414379152,
      "reg_alpha": 0.006768562010233418,
      "reg_lambda": 0.00013596853001557294,
      "scale_pos_weight": 1.7954119100310102
    },
    "user_attrs": {
      "device": "cuda",
      "n_estimators_used": 1118,
      "val_auroc": 0.9017759367920826
    }
  },
  {
    "number": 17,
    "value": 0.1709855900959519,
    "params": {
      "max_depth": 7,
      "learning_rate": 0.032275515482109864,
      "min_child_weight": 21,
      "gamma": 0.6872511320877258,
      "subsample": 0.689231032352721,
      "colsample_bytree": 0.9014217867322246,
      "reg_alpha": 0.0030466772539233904,
      "reg_lambda": 0.00010042713308597354,
      "scale_pos_weight": 2.923496905851235
    },
    "user_attrs": {
      "device": "cuda",
      "n_estimators_used": 4,
      "val_auroc": 0.863083365255665
    }
  },
  {
    "number": 18,
    "value": 0.21202279480497227,
    "params": {
      "max_depth": 7,
      "learning_rate": 0.02857443647015894,
      "min_child_weight": 47,
      "gamma": 0.4327456111804914,
      "subsample": 0.7140919112570762,
      "colsample_bytree": 0.665073630483426,
      "reg_alpha": 0.0005979536270230757,
      "reg_lambda": 6.479872737032084e-08,
      "scale_pos_weight": 2.5111544280078535
    },
    "user_attrs": {
      "device": "cuda",
      "n_estimators_used": 552,
      "val_auroc": 0.8954530368379192
    }
  },
  {
    "number": 19,
    "value": 0.19491726985903707,
    "params": {
      "max_depth": 7,
      "learning_rate": 0.12159374562586443,
      "min_child_weight": 20,
      "gamma": 0.8486711919859846,
      "subsample": 0.8765352429849813,
      "colsample_bytree": 0.9968392191316128,
      "reg_alpha": 0.3906951774746014,
      "reg_lambda": 0.012238619075446225,
      "scale_pos_weight": 21.33002702608126
    },
    "user_attrs": {
      "device": "cuda",
      "n_estimators_used": 103,
      "val_auroc": 0.8900620679106895
    }
  },
  {
    "number": 20,
    "value": 0.15971781023191003,
    "params": {
      "max_depth": 8,
      "learning_rate": 0.00976550522750684,
      "min_child_weight": 42,
      "gamma": 0.6922931334992576,
      "subsample": 0.7284719231522373,
      "colsample_bytree": 0.8854577890385553,
      "reg_alpha": 0.019180934401115693,
      "reg_lambda": 7.321641721863961e-05,
      "scale_pos_weight": 8.066331533752532
    },
    "user_attrs": {
      "device": "cuda",
      "n_estimators_used": 5,
      "val_auroc": 0.8614431012602396
    }
  },
  {
    "number": 21,
    "value": 0.2129242213709447,
    "params": {
      "max_depth": 8,
      "learning_rate": 0.05292918585873519,
      "min_child_weight": 24,
      "gamma": 0.9827855241619002,
      "subsample": 0.8114155462046961,
      "colsample_bytree": 0.7673368154770999,
      "reg_alpha": 0.9706621636930097,
      "reg_lambda": 0.0004445286112008841,
      "scale_pos_weight": 60.3958368296191
    },
    "user_attrs": {
      "device": "cuda",
      "n_estimators_used": 552,
      "val_auroc": 0.8917096948829841
    }
  },
  {
    "number": 22,
    "value": 0.21028143567193774,
    "params": {
      "max_depth": 8,
      "learning_rate": 0.08608067494193346,
      "min_child_weight": 34,
      "gamma": 0.8951887697629463,
      "subsample": 0.8328731897285682,
      "colsample_bytree": 0.7061427337100419,
      "reg_alpha": 0.749553950927222,
      "reg_lambda": 0.02896980871584369,
      "scale_pos_weight": 46.69681149277765
    },
    "user_attrs": {
      "device": "cuda",
      "n_estimators_used": 447,
      "val_auroc": 0.8901122050271042
    }
  },
  {
    "number": 23,
    "value": 0.211515103301182,
    "params": {
      "max_depth": 7,
      "learning_rate": 0.05043027679203658,
      "min_child_weight": 19,
      "gamma": 0.018312198090511433,
      "subsample": 0.7575692446945022,
      "colsample_bytree": 0.8602545657367612,
      "reg_alpha": 0.033608872821702634,
      "reg_lambda": 0.0020045186008761065,
      "scale_pos_weight": 35.64450233809943
    },
    "user_attrs": {
      "device": "cuda",
      "n_estimators_used": 251,
      "val_auroc": 0.8931830388384064
    }
  },
  {
    "number": 24,
    "value": 0.22584409511726222,
    "params": {
      "max_depth": 8,
      "learning_rate": 0.02431089342650725,
      "min_child_weight": 30,
      "gamma": 0.7525134353708258,
      "subsample": 0.6858876497934784,
      "colsample_bytree": 0.749587336328261,
      "reg_alpha": 0.0012697781800061617,
      "reg_lambda": 1.8270153390589201e-06,
      "scale_pos_weight": 56.501291993619766
    },
    "user_attrs": {
      "device": "cuda",
      "n_estimators_used": 1416,
      "val_auroc": 0.8978257332986361
    }
  },
  {
    "number": 25,
    "value": 0.206008832174837,
    "params": {
      "max_depth": 7,
      "learning_rate": 0.08998717174340053,
      "min_child_weight": 41,
      "gamma": 0.8046767172008178,
      "subsample": 0.6379550465148243,
      "colsample_bytree": 0.9337331717771118,
      "reg_alpha": 0.022928121741181615,
      "reg_lambda": 6.39833289930036e-05,
      "scale_pos_weight": 27.894949572807075
    },
    "user_attrs": {
      "device": "cuda",
      "n_estimators_used": 173,
      "val_auroc": 0.8936280380311352
    }
  },
  {
    "number": 26,
    "value": 0.19407605265258931,
    "params": {
      "max_depth": 8,
      "learning_rate": 0.043407117152529984,
      "min_child_weight": 26,
      "gamma": 0.915825864821438,
      "subsample": 0.7833812504180926,
      "colsample_bytree": 0.6385230832258706,
      "reg_alpha": 1.3471646165017994,
      "reg_lambda": 0.00042440611155256287,
      "scale_pos_weight": 45.0953099879158
    },
    "user_attrs": {
      "device": "cuda",
      "n_estimators_used": 202,
      "val_auroc": 0.8919869934320734
    }
  },
  {
    "number": 27,
    "value": 0.20292615806996844,
    "params": {
      "max_depth": 7,
      "learning_rate": 0.1677158649293931,
      "min_child_weight": 5,
      "gamma": 0.6533947272104337,
      "subsample": 0.7291470728880118,
      "colsample_bytree": 0.8294393872516963,
      "reg_alpha": 0.26649356512309125,
      "reg_lambda": 7.634526417724418e-07,
      "scale_pos_weight": 39.79849503341093
    },
    "user_attrs": {
      "device": "cuda",
      "n_estimators_used": 116,
      "val_auroc": 0.8902590398783153
    }
  },
  {
    "number": 28,
    "value": 0.19379743146864728,
    "params": {
      "max_depth": 8,
      "learning_rate": 0.09805116942738071,
      "min_child_weight": 15,
      "gamma": 0.9570458833209272,
      "subsample": 0.85085941566083,
      "colsample_bytree": 0.7963862884784016,
      "reg_alpha": 0.00016236692063835965,
      "reg_lambda": 3.80980467569205e-05,
      "scale_pos_weight": 20.501819081860475
    },
    "user_attrs": {
      "device": "cuda",
      "n_estimators_used": 140,
      "val_auroc": 0.8932375782023632
    }
  },
  {
    "number": 29,
    "value": 0.19097999410525573,
    "params": {
      "max_depth": 5,
      "learning_rate": 0.2697979318598062,
      "min_child_weight": 83,
      "gamma": 0.4938437634337891,
      "subsample": 0.9225491318515666,
      "colsample_bytree": 0.698267763683097,
      "reg_alpha": 1.1286569686596187e-06,
      "reg_lambda": 1.2391844377699314e-08,
      "scale_pos_weight": 37.00355387212987
    },
    "user_attrs": {
      "device": "cuda",
      "n_estimators_used": 120,
      "val_auroc": 0.886057735040805
    }
  },
  {
    "number": 30,
    "value": 0.1758164382643099,
    "params": {
      "max_depth": 3,
      "learning_rate": 0.0632377436417315,
      "min_child_weight": 50,
      "gamma": 0.8486059526638035,
      "subsample": 0.7856856163905416,
      "colsample_bytree": 0.6031643772941133,
      "reg_alpha": 0.01658377435736874,
      "reg_lambda": 0.23884579887982044,
      "scale_pos_weight": 48.009602528285924
    },
    "user_attrs": {
      "device": "cuda",
      "n_estimators_used": 164,
      "val_auroc": 0.8815405398073103
    }
  },
  {
    "number": 31,
    "value": 0.14803609443675153,
    "params": {
      "max_depth": 8,
      "learning_rate": 0.024404376166130184,
      "min_child_weight": 29,
      "gamma": 0.7458105145211968,
      "subsample": 0.6985087017997899,
      "colsample_bytree": 0.7517531748493084,
      "reg_alpha": 0.0009904370028980256,
      "reg_lambda": 9.230567161045204e-06,
      "scale_pos_weight": 56.865690681703775
    },
    "user_attrs": {
      "device": "cuda",
      "n_estimators_used": 3,
      "val_auroc": 0.8593811191687044
    }
  },
  {
    "number": 32,
    "value": 0.1466778721231206,
    "params": {
      "max_depth": 8,
      "learning_rate": 0.012099115042121805,
      "min_child_weight": 36,
      "gamma": 0.6005191311518747,
      "subsample": 0.6765680621476255,
      "colsample_bytree": 0.7489966862198597,
      "reg_alpha": 0.001708821231732314,
      "reg_lambda": 2.854526980379799e-06,
      "scale_pos_weight": 57.37405597338909
    },
    "user_attrs": {
      "device": "cuda",
      "n_estimators_used": 8,
      "val_auroc": 0.8623526971540735
    }
  },
  {
    "number": 33,
    "value": 0.21496250015481047,
    "params": {
      "max_depth": 7,
      "learning_rate": 0.036450355118517394,
      "min_child_weight": 30,
      "gamma": 0.7724038531521317,
      "subsample": 0.6267621687067435,
      "colsample_bytree": 0.8806145586049708,
      "reg_alpha": 5.60733739440593e-05,
      "reg_lambda": 6.145326970254058e-07,
      "scale_pos_weight": 52.94069161758371
    },
    "user_attrs": {
      "device": "cuda",
      "n_estimators_used": 408,
      "val_auroc": 0.8961371611195934
    }
  },
  {
    "number": 34,
    "value": 0.15859174680514435,
    "params": {
      "max_depth": 8,
      "learning_rate": 0.023544934024256278,
      "min_child_weight": 18,
      "gamma": 0.8482760929497781,
      "subsample": 0.7392466178312901,
      "colsample_bytree": 0.9434492785151565,
      "reg_alpha": 0.00040058068428245225,
      "reg_lambda": 0.011927777063802906,
      "scale_pos_weight": 58.221810746081566
    },
    "user_attrs": {
      "device": "cuda",
      "n_estimators_used": 15,
      "val_auroc": 0.8729376436176829
    }
  },
  {
    "number": 35,
    "value": 0.22252103108000074,
    "params": {
      "max_depth": 7,
      "learning_rate": 0.04698933756210499,
      "min_child_weight": 39,
      "gamma": 0.8890116937442254,
      "subsample": 0.6697419880978025,
      "colsample_bytree": 0.4968323454127724,
      "reg_alpha": 1.0175520942589703e-05,
      "reg_lambda": 0.00016950994354232013,
      "scale_pos_weight": 32.682751700438374
    },
    "user_attrs": {
      "device": "cuda",
      "n_estimators_used": 376,
      "val_auroc": 0.8987823890402116
    }
  },
  {
    "number": 36,
    "value": 0.16058034972050778,
    "params": {
      "max_depth": 8,
      "learning_rate": 0.02532894743392112,
      "min_child_weight": 99,
      "gamma": 0.5518069310994134,
      "subsample": 0.6165457351910638,
      "colsample_bytree": 0.8460203261132064,
      "reg_alpha": 0.0514388498815489,
      "reg_lambda": 0.0016404994944913896,
      "scale_pos_weight": 50.64544350616385
    },
    "user_attrs": {
      "device": "cuda",
      "n_estimators_used": 18,
      "val_auroc": 0.8762289982187539
    }
  },
  {
    "number": 37,
    "value": 0.19132766560673536,
    "params": {
      "max_depth": 6,
      "learning_rate": 0.040848546679988613,
      "min_child_weight": 83,
      "gamma": 0.9943963700750977,
      "subsample": 0.5642172125113806,
      "colsample_bytree": 0.5935468496646357,
      "reg_alpha": 1.0511813176549817e-07,
      "reg_lambda": 1.8493467449504076e-05,
      "scale_pos_weight": 44.25442069225215
    },
    "user_attrs": {
      "device": "cuda",
      "n_estimators_used": 249,
      "val_auroc": 0.8910913113912213
    }
  },
  {
    "number": 38,
    "value": 0.19308617554432664,
    "params": {
      "max_depth": 4,
      "learning_rate": 0.05997537835100767,
      "min_child_weight": 59,
      "gamma": 0.6498732110284455,
      "subsample": 0.7114019843530437,
      "colsample_bytree": 0.679364772372818,
      "reg_alpha": 2.3023928966943763,
      "reg_lambda": 7.927756808671358e-07,
      "scale_pos_weight": 53.84806364221916
    },
    "user_attrs": {
      "device": "cuda",
      "n_estimators_used": 318,
      "val_auroc": 0.8918691165084996
    }
  },
  {
    "number": 39,
    "value": 0.20765676131379046,
    "params": {
      "max_depth": 6,
      "learning_rate": 0.01501765029876832,
      "min_child_weight": 46,
      "gamma": 0.3962821569517571,
      "subsample": 0.5152673521593867,
      "colsample_bytree": 0.7442572839379531,
      "reg_alpha": 0.009705850776352177,
      "reg_lambda": 0.03822408614464594,
      "scale_pos_weight": 11.72118781646899
    },
    "user_attrs": {
      "device": "cuda",
      "n_estimators_used": 782,
      "val_auroc": 0.8956433161923905
    }
  },
  {
    "number": 40,
    "value": 0.2230501040627221,
    "params": {
      "max_depth": 8,
      "learning_rate": 0.020796716614965006,
      "min_child_weight": 25,
      "gamma": 0.8164249363521523,
      "subsample": 0.6482291068719241,
      "colsample_bytree": 0.7991735790098703,
      "reg_alpha": 0.2651103468875054,
      "reg_lambda": 0.0009153076024614177,
      "scale_pos_weight": 40.57976046947458
    },
    "user_attrs": {
      "device": "cuda",
      "n_estimators_used": 1258,
      "val_auroc": 0.8989973962590366
    }
  },
  {
    "number": 41,
    "value": 0.1585040403870705,
    "params": {
      "max_depth": 8,
      "learning_rate": 0.020052649454802316,
      "min_child_weight": 24,
      "gamma": 0.8024825908370558,
      "subsample": 0.6423717067715107,
      "colsample_bytree": 0.8065724478821499,
      "reg_alpha": 0.25579631536527614,
      "reg_lambda": 0.0008893345209141207,
      "scale_pos_weight": 40.148612472876295
    },
    "user_attrs": {
      "device": "cuda",
      "n_estimators_used": 15,
      "val_auroc": 0.8748374076643539
    }
  },
  {
    "number": 42,
    "value": 0.2213278176085409,
    "params": {
      "max_depth": 8,
      "learning_rate": 0.03016479100745995,
      "min_child_weight": 8,
      "gamma": 0.7187877721691558,
      "subsample": 0.589399371916949,
      "colsample_bytree": 0.776615188303174,
      "reg_alpha": 3.422927078244485,
      "reg_lambda": 0.006181306209772294,
      "scale_pos_weight": 48.21701106395966
    },
    "user_attrs": {
      "device": "cuda",
      "n_estimators_used": 625,
      "val_auroc": 0.8957892817230755
    }
  },
  {
    "number": 43,
    "value": 0.1560402792637887,
    "params": {
      "max_depth": 8,
      "learning_rate": 0.013367404439331487,
      "min_child_weight": 30,
      "gamma": 0.9396859455881249,
      "subsample": 0.6617611802884951,
      "colsample_bytree": 0.8172471339110924,
      "reg_alpha": 8.886225713978899,
      "reg_lambda": 0.00020027202414614842,
      "scale_pos_weight": 31.451580644953435
    },
    "user_attrs": {
      "device": "cuda",
      "n_estimators_used": 12,
      "val_auroc": 0.872126405356896
    }
  },
  {
    "number": 44,
    "value": 0.1581245276275648,
    "params": {
      "max_depth": 7,
      "learning_rate": 0.0054006246248774065,
      "min_child_weight": 13,
      "gamma": 0.8647447142611941,
      "subsample": 0.7814828827878423,
      "colsample_bytree": 0.8655253392277555,
      "reg_alpha": 0.07824409538563408,
      "reg_lambda": 0.0002900813074581903,
      "scale_pos_weight": 56.44875373987351
    },
    "user_attrs": {
      "device": "cuda",
      "n_estimators_used": 19,
      "val_auroc": 0.8716523663440164
    }
  },
  {
    "number": 45,
    "value": 0.15758517936450206,
    "params": {
      "max_depth": 8,
      "learning_rate": 0.00967130054713554,
      "min_child_weight": 16,
      "gamma": 0.9438047512933462,
      "subsample": 0.7578741633106206,
      "colsample_bytree": 0.9099050019632219,
      "reg_alpha": 0.36783484160334473,
      "reg_lambda": 0.0013505393927328035,
      "scale_pos_weight": 35.72117392925371
    },
    "user_attrs": {
      "device": "cuda",
      "n_estimators_used": 17,
      "val_auroc": 0.8642521861258923
    }
  },
  {
    "number": 46,
    "value": 0.20893262522713404,
    "params": {
      "max_depth": 7,
      "learning_rate": 0.07427617555845065,
      "min_child_weight": 27,
      "gamma": 0.8141288201170562,
      "subsample": 0.6865837965127393,
      "colsample_bytree": 0.7287544048128676,
      "reg_alpha": 0.002031249197994448,
      "reg_lambda": 0.0036843819651373073,
      "scale_pos_weight": 42.133612746240374
    },
    "user_attrs": {
      "device": "cuda",
      "n_estimators_used": 196,
      "val_auroc": 0.8969748611612177
    }
  },
  {
    "number": 47,
    "value": 0.1567387844359534,
    "params": {
      "max_depth": 8,
      "learning_rate": 0.01900209818901892,
      "min_child_weight": 33,
      "gamma": 0.6484994910261208,
      "subsample": 0.5403317102892633,
      "colsample_bytree": 0.971792970629439,
      "reg_alpha": 0.006097704780481194,
      "reg_lambda": 0.3335241926254416,
      "scale_pos_weight": 60.22332114179288
    },
    "user_attrs": {
      "device": "cuda",
      "n_estimators_used": 19,
      "val_auroc": 0.8736251527899069
    }
  },
  {
    "number": 48,
    "value": 0.1574524411781349,
    "params": {
      "max_depth": 4,
      "learning_rate": 0.02189990407792064,
      "min_child_weight": 23,
      "gamma": 0.7628100343414042,
      "subsample": 0.7111413828751583,
      "colsample_bytree": 0.787430844445694,
      "reg_alpha": 0.00018062024054500605,
      "reg_lambda": 2.889425465563325e-05,
      "scale_pos_weight": 27.24568078085298
    },
    "user_attrs": {
      "device": "cuda",
      "n_estimators_used": 15,
      "val_auroc": 0.865820864515745
    }
  },
  {
    "number": 49,
    "value": 0.21304689380460884,
    "params": {
      "max_depth": 6,
      "learning_rate": 0.037042373186691166,
      "min_child_weight": 36,
      "gamma": 0.5701174368424893,
      "subsample": 0.6597066932264561,
      "colsample_bytree": 0.8274114911803385,
      "reg_alpha": 0.13650841402694416,
      "reg_lambda": 5.801880047168826e-06,
      "scale_pos_weight": 51.11504479904612
    },
    "user_attrs": {
      "device": "cuda",
      "n_estimators_used": 437,
      "val_auroc": 0.8959737834557426
    }
  },
  {
    "number": 50,
    "value": 0.23771886284131577,
    "params": {
      "max_depth": 7,
      "learning_rate": 0.11108904389570162,
      "min_child_weight": 64,
      "gamma": 0.32489283656132134,
      "subsample": 0.7496802905267776,
      "colsample_bytree": 0.4130496784074723,
      "reg_alpha": 2.2023198250349054,
      "reg_lambda": 0.04530070217738001,
      "scale_pos_weight": 7.454306172575695
    },
    "user_attrs": {
      "device": "cuda",
      "n_estimators_used": 517,
      "val_auroc": 0.8978477382369228
    }
  },
  {
    "number": 51,
    "value": 0.2289512371205601,
    "params": {
      "max_depth": 7,
      "learning_rate": 0.16809627959905465,
      "min_child_weight": 80,
      "gamma": 0.2796446981168599,
      "subsample": 0.7500880358109536,
      "colsample_bytree": 0.31461514125277734,
      "reg_alpha": 2.275981853951256,
      "reg_lambda": 0.06399395359044399,
      "scale_pos_weight": 5.999304437960172
    },
    "user_attrs": {
      "device": "cuda",
      "n_estimators_used": 310,
      "val_auroc": 0.8955642815178194
    }
  },
  {
    "number": 52,
    "value": 0.2005502290955377,
    "params": {
      "max_depth": 7,
      "learning_rate": 0.2118115141788275,
      "min_child_weight": 66,
      "gamma": 0.2717302741689633,
      "subsample": 0.8056712850637308,
      "colsample_bytree": 0.39279639064485145,
      "reg_alpha": 2.203209050993449,
      "reg_lambda": 0.07562535766919269,
      "scale_pos_weight": 6.617647452391704
    },
    "user_attrs": {
      "device": "cuda",
      "n_estimators_used": 204,
      "val_auroc": 0.8881941936486224
    }
  },
  {
    "number": 53,
    "value": 0.21271030645203431,
    "params": {
      "max_depth": 6,
      "learning_rate": 0.1618498992148622,
      "min_child_weight": 90,
      "gamma": 0.34391346194224215,
      "subsample": 0.7484963743382649,
      "colsample_bytree": 0.3079641147875408,
      "reg_alpha": 0.7376798548852408,
      "reg_lambda": 2.767273165671379,
      "scale_pos_weight": 5.558378868273853
    },
    "user_attrs": {
      "device": "cuda",
      "n_estimators_used": 383,
      "val_auroc": 0.8948546519178671
    }
  },
  {
    "number": 54,
    "value": 0.1997450417334618,
    "params": {
      "max_depth": 7,
      "learning_rate": 0.11011968439094937,
      "min_child_weight": 80,
      "gamma": 0.2070038366181186,
      "subsample": 0.7712688409188516,
      "colsample_bytree": 0.44332660571106164,
      "reg_alpha": 5.445350182659794,
      "reg_lambda": 0.01927577675150511,
      "scale_pos_weight": 1.279450329452128
    },
    "user_attrs": {
      "device": "cuda",
      "n_estimators_used": 149,
      "val_auroc": 0.8898624433605656
    }
  },
  {
    "number": 55,
    "value": 0.19503510780532277,
    "params": {
      "max_depth": 7,
      "learning_rate": 0.1903278611384154,
      "min_child_weight": 73,
      "gamma": 0.24106068913411077,
      "subsample": 0.7316769616396638,
      "colsample_bytree": 0.32338371978221525,
      "reg_alpha": 9.322861967644885,
      "reg_lambda": 0.12267079756262625,
      "scale_pos_weight": 15.367519681910634
    },
    "user_attrs": {
      "device": "cuda",
      "n_estimators_used": 144,
      "val_auroc": 0.8916198792690175
    }
  },
  {
    "number": 56,
    "value": 0.208121151305947,
    "params": {
      "max_depth": 6,
      "learning_rate": 0.1400962260417771,
      "min_child_weight": 93,
      "gamma": 0.47620056374552266,
      "subsample": 0.8039193819335029,
      "colsample_bytree": 0.3755425330492376,
      "reg_alpha": 1.4945894989314055,
      "reg_lambda": 0.6536633559011847,
      "scale_pos_weight": 10.909790392984107
    },
    "user_attrs": {
      "device": "cuda",
      "n_estimators_used": 181,
      "val_auroc": 0.8940872513493944
    }
  },
  {
    "number": 57,
    "value": 0.22519528250131224,
    "params": {
      "max_depth": 7,
      "learning_rate": 0.07580877963645803,
      "min_child_weight": 65,
      "gamma": 0.08996709621839644,
      "subsample": 0.6993776553051066,
      "colsample_bytree": 0.44977776875922776,
      "reg_alpha": 0.49854486201110354,
      "reg_lambda": 0.00558740826038874,
      "scale_pos_weight": 8.498666376508968
    },
    "user_attrs": {
      "device": "cuda",
      "n_estimators_used": 567,
      "val_auroc": 0.9008377163151369
    }
  },
  {
    "number": 58,
    "value": 0.20023879822816382,
    "params": {
      "max_depth": 5,
      "learning_rate": 0.10575663495424131,
      "min_child_weight": 54,
      "gamma": 0.3793072182354849,
      "subsample": 0.8406753718276974,
      "colsample_bytree": 0.34770698750496676,
      "reg_alpha": 0.053286632716924645,
      "reg_lambda": 1.4582699132265744,
      "scale_pos_weight": 3.8257210005600566
    },
    "user_attrs": {
      "device": "cuda",
      "n_estimators_used": 214,
      "val_auroc": 0.8928852991830635
    }
  },
  {
    "number": 59,
    "value": 0.21164211463549443,
    "params": {
      "max_depth": 7,
      "learning_rate": 0.1310835797641312,
      "min_child_weight": 60,
      "gamma": 0.2978332370529616,
      "subsample": 0.7686201897044774,
      "colsample_bytree": 0.5322128681166841,
      "reg_alpha": 3.57174031390215,
      "reg_lambda": 0.05115454846985118,
      "scale_pos_weight": 3.9129264867481086
    },
    "user_attrs": {
      "device": "cuda",
      "n_estimators_used": 171,
      "val_auroc": 0.8933839117244062
    }
  },
  {
    "number": 60,
    "value": 0.22251076301200273,
    "params": {
      "max_depth": 8,
      "learning_rate": 0.08586173330315384,
      "min_child_weight": 78,
      "gamma": 0.14043758338766263,
      "subsample": 0.7161834644747231,
      "colsample_bytree": 0.4804319504458467,
      "reg_alpha": 0.012510552548353229,
      "reg_lambda": 7.235049514315007,
      "scale_pos_weight": 9.310905904841558
    },
    "user_attrs": {
      "device": "cuda",
      "n_estimators_used": 389,
      "val_auroc": 0.8982613578983996
    }
  },
  {
    "number": 61,
    "value": 0.21278938004533274,
    "params": {
      "max_depth": 7,
      "learning_rate": 0.07183438768085464,
      "min_child_weight": 64,
      "gamma": 0.0577081664186265,
      "subsample": 0.6945369924677295,
      "colsample_bytree": 0.44823799039057155,
      "reg_alpha": 0.8037247346121653,
      "reg_lambda": 0.011569339191494592,
      "scale_pos_weight": 15.674285376687878
    },
    "user_attrs": {
      "device": "cuda",
      "n_estimators_used": 388,
      "val_auroc": 0.8975827545369974
    }
  },
  {
    "number": 62,
    "value": 0.24490599117419493,
    "params": {
      "max_depth": 7,
      "learning_rate": 0.06353796183578202,
      "min_child_weight": 69,
      "gamma": 0.062073449798525665,
      "subsample": 0.7437385815722544,
      "colsample_bytree": 0.41109416111448455,
      "reg_alpha": 0.5348460712130395,
      "reg_lambda": 0.004950209493115474,
      "scale_pos_weight": 8.728404245489292
    },
    "user_attrs": {
      "device": "cuda",
      "n_estimators_used": 1093,
      "val_auroc": 0.90198883790345
    }
  },
  {
    "number": 63,
    "value": 0.2065658719581746,
    "params": {
      "max_depth": 6,
      "learning_rate": 0.056368766282460736,
      "min_child_weight": 69,
      "gamma": 0.1149693135071285,
      "subsample": 0.7988960560469696,
      "colsample_bytree": 0.4161991327461781,
      "reg_alpha": 0.13887919249420239,
      "reg_lambda": 0.0025130293188051537,
      "scale_pos_weight": 6.7648707210322545
    },
    "user_attrs": {
      "device": "cuda",
      "n_estimators_used": 298,
      "val_auroc": 0.8952427100912008
    }
  },
  {
    "number": 64,
    "value": 0.22460626345212076,
    "params": {
      "max_depth": 7,
      "learning_rate": 0.06435891171077174,
      "min_child_weight": 75,
      "gamma": 0.1755442094497932,
      "subsample": 0.7521604000965586,
      "colsample_bytree": 0.3044405240548538,
      "reg_alpha": 1.5619087541011984,
      "reg_lambda": 0.17949545221298455,
      "scale_pos_weight": 19.436133422397575
    },
    "user_attrs": {
      "device": "cuda",
      "n_estimators_used": 648,
      "val_auroc": 0.9004490061514087
    }
  },
  {
    "number": 65,
    "value": 0.18933889833632106,
    "params": {
      "max_depth": 7,
      "learning_rate": 0.2983921403098939,
      "min_child_weight": 69,
      "gamma": 0.43195148448300874,
      "subsample": 0.8253120955410136,
      "colsample_bytree": 0.38384449646337504,
      "reg_alpha": 4.26986141802014,
      "reg_lambda": 0.007841411329978516,
      "scale_pos_weight": 1.7509708752216873
    },
    "user_attrs": {
      "device": "cuda",
      "n_estimators_used": 208,
      "val_auroc": 0.8884459931788575
    }
  },
  {
    "number": 66,
    "value": 0.25103991198375897,
    "params": {
      "max_depth": 8,
      "learning_rate": 0.04562266664887239,
      "min_child_weight": 50,
      "gamma": 0.02365398547329011,
      "subsample": 0.7409959993645173,
      "colsample_bytree": 0.5671019490726275,
      "reg_alpha": 0.03378698107197232,
      "reg_lambda": 1.560177666444983e-07,
      "scale_pos_weight": 13.158640115801283
    },
    "user_attrs": {
      "device": "cuda",
      "n_estimators_used": 863,
      "val_auroc": 0.9009746106751175
    }
  },
  {
    "number": 67,
    "value": 0.2207858236302927,
    "params": {
      "max_depth": 8,
      "learning_rate": 0.04749111820748447,
      "min_child_weight": 58,
      "gamma": 0.08566044772422005,
      "subsample": 0.741977567532144,
      "colsample_bytree": 0.5701285762180635,
      "reg_alpha": 0.02589638673469073,
      "reg_lambda": 5.595086856742128e-08,
      "scale_pos_weight": 13.710364442060806
    },
    "user_attrs": {
      "device": "cuda",
      "n_estimators_used": 513,
      "val_auroc": 0.9000884848606255
    }
  },
  {
    "number": 68,
    "value": 0.23802323526897184,
    "params": {
      "max_depth": 7,
      "learning_rate": 0.08578892783421996,
      "min_child_weight": 61,
      "gamma": 0.041624857050190055,
      "subsample": 0.7718160319746351,
      "colsample_bytree": 0.49505572597240044,
      "reg_alpha": 0.15804179999728726,
      "reg_lambda": 0.01906147396154913,
      "scale_pos_weight": 10.161475015560423
    },
    "user_attrs": {
      "device": "cuda",
      "n_estimators_used": 601,
      "val_auroc": 0.8983355750883899
    }
  },
  {
    "number": 69,
    "value": 0.207349314724865,
    "params": {
      "max_depth": 6,
      "learning_rate": 0.091490014112311,
      "min_child_weight": 62,
      "gamma": 0.03187757958347445,
      "subsample": 0.7228143293051363,
      "colsample_bytree": 0.48447492963423544,
      "reg_alpha": 0.05533702964941976,
      "reg_lambda": 0.017387014672419765,
      "scale_pos_weight": 18.0531048891184
    },
    "user_attrs": {
      "device": "cuda",
      "n_estimators_used": 232,
      "val_auroc": 0.8959530431268443
    }
  },
  {
    "number": 70,
    "value": 0.21366332860559184,
    "params": {
      "max_depth": 7,
      "learning_rate": 0.10767587357338088,
      "min_child_weight": 53,
      "gamma": 0.1706167952472216,
      "subsample": 0.7709242651771065,
      "colsample_bytree": 0.5085699096943337,
      "reg_alpha": 0.17966105464403062,
      "reg_lambda": 0.06443058479657873,
      "scale_pos_weight": 10.253964387289038
    },
    "user_attrs": {
      "device": "cuda",
      "n_estimators_used": 372,
      "val_auroc": 0.8973482359019256
    }
  },
  {
    "number": 71,
    "value": 0.22400455166847827,
    "params": {
      "max_depth": 7,
      "learning_rate": 0.07883571451713646,
      "min_child_weight": 50,
      "gamma": 0.04286481236975448,
      "subsample": 0.7442019703037248,
      "colsample_bytree": 0.366165721609583,
      "reg_alpha": 0.860643161302284,
      "reg_lambda": 0.026223611281065755,
      "scale_pos_weight": 5.5085655370484945
    },
    "user_attrs": {
      "device": "cuda",
      "n_estimators_used": 510,
      "val_auroc": 0.8979336403336672
    }
  },
  {
    "number": 72,
    "value": 0.22227529917973424,
    "params": {
      "max_depth": 7,
      "learning_rate": 0.05134142247754707,
      "min_child_weight": 56,
      "gamma": 0.06882675960991541,
      "subsample": 0.7956531696404038,
      "colsample_bytree": 0.5497986201414897,
      "reg_alpha": 0.5199129562342023,
      "reg_lambda": 1.8342780628395422e-07,
      "scale_pos_weight": 13.971886885611173
    },
    "user_attrs": {
      "device": "cuda",
      "n_estimators_used": 538,
      "val_auroc": 0.8988148599466889
    }
  },
  {
    "number": 73,
    "value": 0.2500438404614852,
    "params": {
      "max_depth": 8,
      "learning_rate": 0.06715978307666981,
      "min_child_weight": 68,
      "gamma": 0.0978635949403513,
      "subsample": 0.7635032000152278,
      "colsample_bytree": 0.6368664204477883,
      "reg_alpha": 0.035277310164469194,
      "reg_lambda": 0.0034076952719365294,
      "scale_pos_weight": 7.802206707749793
    },
    "user_attrs": {
      "device": "cuda",
      "n_estimators_used": 842,
      "val_auroc": 0.8980288220070634
    }
  },
  {
    "number": 74,
    "value": 0.21128940134074356,
    "params": {
      "max_depth": 7,
      "learning_rate": 0.0432537282951061,
      "min_child_weight": 68,
      "gamma": 0.008838483990600013,
      "subsample": 0.7618030312135012,
      "colsample_bytree": 0.6237804387233631,
      "reg_alpha": 0.004488978309148601,
      "reg_lambda": 0.0025506772841574297,
      "scale_pos_weight": 11.933318451350443
    },
    "user_attrs": {
      "device": "cuda",
      "n_estimators_used": 289,
      "val_auroc": 0.8952229855444385
    }
  },
  {
    "number": 75,
    "value": 0.22864029620691123,
    "params": {
      "max_depth": 8,
      "learning_rate": 0.1589613083220925,
      "min_child_weight": 72,
      "gamma": 0.09837188388145783,
      "subsample": 0.7342364985262424,
      "colsample_bytree": 0.5789964508551302,
      "reg_alpha": 0.09075607050724009,
      "reg_lambda": 1.0438314554010263e-08,
      "scale_pos_weight": 7.966608400955887
    },
    "user_attrs": {
      "device": "cuda",
      "n_estimators_used": 449,
      "val_auroc": 0.8934029984544782
    }
  },
  {
    "number": 76,
    "value": 0.21241100290857157,
    "params": {
      "max_depth": 8,
      "learning_rate": 0.0584605965296475,
      "min_child_weight": 62,
      "gamma": 0.22032379236613842,
      "subsample": 0.7936073135611579,
      "colsample_bytree": 0.6143650598602659,
      "reg_alpha": 0.03885154773855844,
      "reg_lambda": 0.008909019387874851,
      "scale_pos_weight": 22.719789481092135
    },
    "user_attrs": {
      "device": "cuda",
      "n_estimators_used": 210,
      "val_auroc": 0.8952685776263649
    }
  },
  {
    "number": 77,
    "value": 0.2146917486010718,
    "params": {
      "max_depth": 7,
      "learning_rate": 0.03286711283991569,
      "min_child_weight": 75,
      "gamma": 0.0043670998585396276,
      "subsample": 0.7233824024011878,
      "colsample_bytree": 0.6558001922453902,
      "reg_alpha": 0.011220855929110233,
      "reg_lambda": 0.0006050226888127935,
      "scale_pos_weight": 4.294080595084103
    },
    "user_attrs": {
      "device": "cuda",
      "n_estimators_used": 531,
      "val_auroc": 0.8959591735163981
    }
  },
  {
    "number": 78,
    "value": 0.23617959217065027,
    "params": {
      "max_depth": 8,
      "learning_rate": 0.06271962100951478,
      "min_child_weight": 67,
      "gamma": 0.12135519364285294,
      "subsample": 0.8699831425864443,
      "colsample_bytree": 0.4004742108040568,
      "reg_alpha": 0.020931762922713967,
      "reg_lambda": 0.03696046820589231,
      "scale_pos_weight": 7.0303004750044575
    },
    "user_attrs": {
      "device": "cuda",
      "n_estimators_used": 802,
      "val_auroc": 0.9009270311248876
    }
  },
  {
    "number": 79,
    "value": 0.224808944419411,
    "params": {
      "max_depth": 8,
      "learning_rate": 0.06761714542619437,
      "min_child_weight": 67,
      "gamma": 0.13598606485853867,
      "subsample": 0.9844594541864569,
      "colsample_bytree": 0.46878587508048886,
      "reg_alpha": 0.030939645672401997,
      "reg_lambda": 0.030171659165517783,
      "scale_pos_weight": 9.645808911267373
    },
    "user_attrs": {
      "device": "cuda",
      "n_estimators_used": 524,
      "val_auroc": 0.8978094204149762
    }
  },
  {
    "number": 80,
    "value": 0.23878784514082102,
    "params": {
      "max_depth": 8,
      "learning_rate": 0.0550053651620321,
      "min_child_weight": 45,
      "gamma": 0.11657450236359504,
      "subsample": 0.8638344375782174,
      "colsample_bytree": 0.40985369477067074,
      "reg_alpha": 0.003519153629407941,
      "reg_lambda": 0.004345240514428213,
      "scale_pos_weight": 3.05739778733685
    },
    "user_attrs": {
      "device": "cuda",
      "n_estimators_used": 649,
      "val_auroc": 0.9018277684535801
    }
  },
  {
    "number": 81,
    "value": 0.23969702269005572,
    "params": {
      "max_depth": 8,
      "learning_rate": 0.08243751065042738,
      "min_child_weight": 49,
      "gamma": 0.17116424421992213,
      "subsample": 0.8591099241325167,
      "colsample_bytree": 0.41213787428838267,
      "reg_alpha": 0.0007630853733046538,
      "reg_lambda": 0.003273478532366842,
      "scale_pos_weight": 7.695352549512873
    },
    "user_attrs": {
      "device": "cuda",
      "n_estimators_used": 768,
      "val_auroc": 0.8973186858284229
    }
  },
  {
    "number": 82,
    "value": 0.23268051781955246,
    "params": {
      "max_depth": 8,
      "learning_rate": 0.08305118147358707,
      "min_child_weight": 47,
      "gamma": 0.16807802192209104,
      "subsample": 0.8694867913178652,
      "colsample_bytree": 0.424625987710055,
      "reg_alpha": 0.0007488573002676274,
      "reg_lambda": 0.003721832696577115,
      "scale_pos_weight": 7.843186280803293
    },
    "user_attrs": {
      "device": "cuda",
      "n_estimators_used": 844,
      "val_auroc": 0.8973545185275618
    }
  },
  {
    "number": 83,
    "value": 0.21269131568884886,
    "params": {
      "max_depth": 8,
      "learning_rate": 0.053527835019701354,
      "min_child_weight": 50,
      "gamma": 0.12118822165143492,
      "subsample": 0.9103888637936683,
      "colsample_bytree": 0.3999865020674555,
      "reg_alpha": 0.002775616629794242,
      "reg_lambda": 0.02004803603870762,
      "scale_pos_weight": 12.560660997677182
    },
    "user_attrs": {
      "device": "cuda",
      "n_estimators_used": 276,
      "val_auroc": 0.8968921717707645
    }
  },
  {
    "number": 84,
    "value": 0.21176449277212478,
    "params": {
      "max_depth": 8,
      "learning_rate": 0.09822921859326456,
      "min_child_weight": 44,
      "gamma": 0.0495536446423101,
      "subsample": 0.9285860133537924,
      "colsample_bytree": 0.43194478053655966,
      "reg_alpha": 0.00044817477852782074,
      "reg_lambda": 0.0010978882212701467,
      "scale_pos_weight": 3.0274254924735136
    },
    "user_attrs": {
      "device": "cuda",
      "n_estimators_used": 425,
      "val_auroc": 0.8961331326378811
    }
  },
  {
    "number": 85,
    "value": 0.23410877433826527,
    "params": {
      "max_depth": 8,
      "learning_rate": 0.06348133615717629,
      "min_child_weight": 60,
      "gamma": 0.07002127061596797,
      "subsample": 0.8724920953083428,
      "colsample_bytree": 0.5150813275269852,
      "reg_alpha": 0.01784661431015476,
      "reg_lambda": 0.005587043005351834,
      "scale_pos_weight": 10.74539920530873
    },
    "user_attrs": {
      "device": "cuda",
      "n_estimators_used": 420,
      "val_auroc": 0.8999418374172816
    }
  },
  {
    "number": 86,
    "value": 0.2445507778421332,
    "params": {
      "max_depth": 8,
      "learning_rate": 0.04572578155978214,
      "min_child_weight": 56,
      "gamma": 0.11053180220171036,
      "subsample": 0.8515679180633537,
      "colsample_bytree": 0.40583409378046975,
      "reg_alpha": 1.0185267139205113e-08,
      "reg_lambda": 0.00027325065298009133,
      "scale_pos_weight": 4.694004719000927
    },
    "user_attrs": {
      "device": "cuda",
      "n_estimators_used": 989,
      "val_auroc": 0.9003159229430086
    }
  },
  {
    "number": 87,
    "value": 0.210114937655303,
    "params": {
      "max_depth": 8,
      "learning_rate": 0.046718524976897914,
      "min_child_weight": 56,
      "gamma": 0.16246596937252694,
      "subsample": 0.8465994726857233,
      "colsample_bytree": 0.3324025078898893,
      "reg_alpha": 1.4631074265973038e-08,
      "reg_lambda": 0.0005671622897019942,
      "scale_pos_weight": 17.35802296541413
    },
    "user_attrs": {
      "device": "cuda",
      "n_estimators_used": 385,
      "val_auroc": 0.8994873334434892
    }
  },
  {
    "number": 88,
    "value": 0.22527072221478875,
    "params": {
      "max_depth": 8,
      "learning_rate": 0.04066278103060283,
      "min_child_weight": 41,
      "gamma": 0.029184114567945223,
      "subsample": 0.8873985074351571,
      "colsample_bytree": 0.470487058704957,
      "reg_alpha": 5.6693276795360786e-08,
      "reg_lambda": 0.0002742143576432442,
      "scale_pos_weight": 4.353905604060764
    },
    "user_attrs": {
      "device": "cuda",
      "n_estimators_used": 721,
      "val_auroc": 0.901269813762356
    }
  },
  {
    "number": 89,
    "value": 0.2332678303864549,
    "params": {
      "max_depth": 8,
      "learning_rate": 0.11781641144184983,
      "min_child_weight": 51,
      "gamma": 0.08770270715478583,
      "subsample": 0.8156620834404398,
      "colsample_bytree": 0.37023497364496766,
      "reg_alpha": 5.0641297299443966e-05,
      "reg_lambda": 0.0021936773849763453,
      "scale_pos_weight": 9.016543411727078
    },
    "user_attrs": {
      "device": "cuda",
      "n_estimators_used": 406,
      "val_auroc": 0.8965976253984884
    }
  },
  {
    "number": 90,
    "value": 0.2239442181752115,
    "params": {
      "max_depth": 8,
      "learning_rate": 0.09632630037759686,
      "min_child_weight": 39,
      "gamma": 0.23764727480389924,
      "subsample": 0.9424062390190541,
      "colsample_bytree": 0.5426050916435351,
      "reg_alpha": 0.2140442416367232,
      "reg_lambda": 0.004280020824726667,
      "scale_pos_weight": 5.191873065863881
    },
    "user_attrs": {
      "device": "cuda",
      "n_estimators_used": 499,
      "val_auroc": 0.8959619074664575
    }
  },
  {
    "number": 91,
    "value": 0.2508266958399683,
    "params": {
      "max_depth": 8,
      "learning_rate": 0.0585349061928459,
      "min_child_weight": 71,
      "gamma": 0.11427894500493307,
      "subsample": 0.8621343692662088,
      "colsample_bytree": 0.4105661403913354,
      "reg_alpha": 1.2155638058897579e-06,
      "reg_lambda": 0.012820484556758601,
      "scale_pos_weight": 7.21752614843287
    },
    "user_attrs": {
      "device": "cuda",
      "n_estimators_used": 1003,
      "val_auroc": 0.9020251120872278
    }
  },
  {
    "number": 92,
    "value": 0.23342250940644346,
    "params": {
      "max_depth": 8,
      "learning_rate": 0.05482213572052564,
      "min_child_weight": 71,
      "gamma": 0.19356411953924738,
      "subsample": 0.8861470698454008,
      "colsample_bytree": 0.4275581804353379,
      "reg_alpha": 3.663010936439103e-07,
      "reg_lambda": 0.011873056626621591,
      "scale_pos_weight": 2.590074285148951
    },
    "user_attrs": {
      "device": "cuda",
      "n_estimators_used": 890,
      "val_auroc": 0.8998360170664839
    }
  },
  {
    "number": 93,
    "value": 0.215398514297025,
    "params": {
      "max_depth": 8,
      "learning_rate": 0.06887106563510477,
      "min_child_weight": 46,
      "gamma": 0.0003055181339713456,
      "subsample": 0.8535306576925394,
      "colsample_bytree": 0.3590594393798682,
      "reg_alpha": 1.4460947065371293e-06,
      "reg_lambda": 0.001812670351338011,
      "scale_pos_weight": 7.339634046178032
    },
    "user_attrs": {
      "device": "cuda",
      "n_estimators_used": 353,
      "val_auroc": 0.8978375714913767
    }
  },
  {
    "number": 94,
    "value": 0.20897602902175944,
    "params": {
      "max_depth": 8,
      "learning_rate": 0.07934267194636323,
      "min_child_weight": 63,
      "gamma": 0.11557565972193759,
      "subsample": 0.8306129159642247,
      "colsample_bytree": 0.40831576268191605,
      "reg_alpha": 1.215382028444114e-05,
      "reg_lambda": 0.0031870498761378025,
      "scale_pos_weight": 14.340527447139527
    },
    "user_attrs": {
      "device": "cuda",
      "n_estimators_used": 196,
      "val_auroc": 0.8925369016589134
    }
  },
  {
    "number": 95,
    "value": 0.23052128386460713,
    "params": {
      "max_depth": 8,
      "learning_rate": 0.04765090967406655,
      "min_child_weight": 55,
      "gamma": 0.1499609757929249,
      "subsample": 0.8939140568131292,
      "colsample_bytree": 0.3827654484932381,
      "reg_alpha": 3.087150443223931e-06,
      "reg_lambda": 0.0008964118191133164,
      "scale_pos_weight": 11.327659364903097
    },
    "user_attrs": {
      "device": "cuda",
      "n_estimators_used": 438,
      "val_auroc": 0.8994847485798001
    }
  },
  {
    "number": 96,
    "value": 0.2230099892748177,
    "params": {
      "max_depth": 8,
      "learning_rate": 0.05947737596422076,
      "min_child_weight": 48,
      "gamma": 0.06423379237218754,
      "subsample": 0.858152964936386,
      "colsample_bytree": 0.46161439440216256,
      "reg_alpha": 3.207158326022808e-07,
      "reg_lambda": 0.007626200750391093,
      "scale_pos_weight": 9.460646387138011
    },
    "user_attrs": {
      "device": "cuda",
      "n_estimators_used": 538,
      "val_auroc": 0.8976274442264215
    }
  },
  {
    "number": 97,
    "value": 0.23200791522653788,
    "params": {
      "max_depth": 8,
      "learning_rate": 0.043531440030477986,
      "min_child_weight": 58,
      "gamma": 0.10395721348283596,
      "subsample": 0.9077603751675216,
      "colsample_bytree": 0.3390631997353373,
      "reg_alpha": 2.2406617522049516e-07,
      "reg_lambda": 0.3657527070997156,
      "scale_pos_weight": 5.118205631641345
    },
    "user_attrs": {
      "device": "cuda",
      "n_estimators_used": 766,
      "val_auroc": 0.8998593181112788
    }
  },
  {
    "number": 98,
    "value": 0.20219755112355609,
    "params": {
      "max_depth": 8,
      "learning_rate": 0.06888324483601056,
      "min_child_weight": 52,
      "gamma": 0.19080241389957084,
      "subsample": 0.8184774029722882,
      "colsample_bytree": 0.677906755762878,
      "reg_alpha": 3.079510466023466e-08,
      "reg_lambda": 0.12555477618747823,
      "scale_pos_weight": 1.227996111434791
    },
    "user_attrs": {
      "device": "cuda",
      "n_estimators_used": 249,
      "val_auroc": 0.8949276895406946
    }
  },
  {
    "number": 99,
    "value": 0.22356296708748455,
    "params": {
      "max_depth": 8,
      "learning_rate": 0.033613331846213235,
      "min_child_weight": 61,
      "gamma": 0.33918754460860157,
      "subsample": 0.8618910817623942,
      "colsample_bytree": 0.49528577026271703,
      "reg_alpha": 0.00021132314880148225,
      "reg_lambda": 0.015075974525030027,
      "scale_pos_weight": 3.1533190149617907
    },
    "user_attrs": {
      "device": "cuda",
      "n_estimators_used": 655,
      "val_auroc": 0.8997766035231293
    }
  }
]